{
  "id" : "FormVerificacionModBD1",
  "name" : "FormVerificacionModBD1",
  "type" : "form",
  "uuid" : "8ebdfc72-5880-4de3-9b75-5e75bb12b020",
  "modelVersion" : "2.6",
  "lastUpdate" : 1722539260634,
  "description" : "Page generated with Bonita UI designer",
  "rows" : [
    [
      {
        "type" : "container",
        "dimension" : {
          "xs" : 12
        },
        "propertyValues" : { },
        "reference" : "02178805-a3ed-42ae-8f48-e7a0ebceb257",
        "hasValidationError" : false,
        "id" : "pbContainer",
        "rows" : [
          [
            {
              "type" : "component",
              "dimension" : {
                "md" : 12,
                "sm" : 12,
                "xs" : 12,
                "lg" : 12
              },
              "propertyValues" : {
                "hidden" : {
                  "type" : "constant",
                  "value" : false
                },
                "level" : {
                  "type" : "constant",
                  "value" : "Level 1"
                },
                "cssClasses" : {
                  "type" : "constant",
                  "value" : ""
                },
                "text" : {
                  "type" : "interpolation",
                  "value" : "{{ task.displayName }}"
                },
                "alignment" : {
                  "type" : "constant",
                  "value" : "center"
                },
                "dimension" : {
                  "type" : "constant",
                  "value" : 12
                }
              },
              "reference" : "6b642aff-c10c-40e9-a278-338ea9acea49",
              "hasValidationError" : false,
              "id" : "pbTitle",
              "description" : ""
            }
          ],
          [
            {
              "type" : "component",
              "dimension" : {
                "md" : 12,
                "sm" : 12,
                "xs" : 12,
                "lg" : 12
              },
              "propertyValues" : {
                "allowHtml" : {
                  "type" : "constant",
                  "value" : true
                },
                "labelHidden" : {
                  "type" : "constant",
                  "value" : true
                },
                "hidden" : {
                  "type" : "constant",
                  "value" : false
                },
                "cssClasses" : {
                  "type" : "constant",
                  "value" : ""
                },
                "label" : {
                  "type" : "interpolation"
                },
                "text" : {
                  "type" : "interpolation",
                  "value" : "{{ task.displayDescription }}"
                },
                "alignment" : {
                  "type" : "constant",
                  "value" : "left"
                },
                "dimension" : {
                  "type" : "constant",
                  "value" : 12
                }
              },
              "reference" : "61bf3e9a-0538-4b9f-8e16-847de36f17cf",
              "hasValidationError" : false,
              "id" : "pbText",
              "description" : ""
            }
          ]
        ]
      }
    ],
    [
      {
        "type" : "formContainer",
        "dimension" : {
          "xs" : 12
        },
        "propertyValues" : {
          "cssClasses" : {
            "type" : "constant",
            "value" : ""
          },
          "hidden" : {
            "type" : "constant",
            "value" : false
          }
        },
        "reference" : "b7168adc-125a-4fe4-87a9-50dbdaba904f",
        "hasValidationError" : false,
        "id" : "pbFormContainer",
        "container" : {
          "type" : "container",
          "dimension" : {
            "xs" : 12
          },
          "propertyValues" : { },
          "reference" : "710791ba-e9b5-4ede-beb7-6ea33345a05c",
          "hasValidationError" : false,
          "id" : "pbContainer",
          "rows" : [
            [
              {
                "type" : "fragment",
                "dimension" : {
                  "xs" : 12,
                  "sm" : 12,
                  "md" : 12,
                  "lg" : 12
                },
                "propertyValues" : {
                  "cssClasses" : {
                    "type" : "constant",
                    "value" : ""
                  },
                  "hidden" : {
                    "type" : "constant",
                    "value" : false
                  }
                },
                "reference" : "bd49c4b0-93d2-4af0-95ec-028c6d7b295e",
                "hasValidationError" : false,
                "id" : "infoSolicitante",
                "binding" : {
                  "solicitud" : "solicitud"
                }
              }
            ],
            [
              {
                "type" : "component",
                "dimension" : {
                  "md" : 2,
                  "sm" : 12,
                  "xs" : 12,
                  "lg" : 6
                },
                "propertyValues" : {
                  "labelHidden" : {
                    "type" : "constant",
                    "value" : false
                  },
                  "hidden" : {
                    "type" : "expression",
                    "value" : "!solicitud.aprobadoArea"
                  },
                  "cssClasses" : {
                    "type" : "constant",
                    "value" : ""
                  },
                  "disabled" : {
                    "type" : "constant",
                    "value" : true
                  },
                  "label" : {
                    "type" : "interpolation",
                    "value" : "Aprobado Area"
                  },
                  "dimension" : {
                    "type" : "constant",
                    "value" : 12
                  },
                  "value" : {
                    "type" : "variable",
                    "value" : "solicitud.aprobadoArea"
                  },
                  "required" : {
                    "type" : "constant",
                    "value" : false
                  },
                  "allowHTML" : {
                    "type" : "constant",
                    "value" : false
                  }
                },
                "reference" : "e9964793-32eb-4f00-a821-5137fc81dd15",
                "hasValidationError" : false,
                "id" : "pbCheckbox",
                "description" : ""
              },
              {
                "type" : "component",
                "dimension" : {
                  "md" : 10,
                  "sm" : 12,
                  "xs" : 12,
                  "lg" : 6
                },
                "propertyValues" : {
                  "allowHtml" : {
                    "type" : "constant",
                    "value" : true
                  },
                  "labelHidden" : {
                    "type" : "constant",
                    "value" : false
                  },
                  "hidden" : {
                    "type" : "expression",
                    "value" : "!solicitud.aprobadoComentario"
                  },
                  "cssClasses" : {
                    "type" : "constant",
                    "value" : ""
                  },
                  "label" : {
                    "type" : "interpolation",
                    "value" : "Aprobado Comentario"
                  },
                  "text" : {
                    "type" : "interpolation",
                    "value" : "{{solicitud.aprobadoComentario}}"
                  },
                  "alignment" : {
                    "type" : "constant",
                    "value" : "left"
                  },
                  "dimension" : {
                    "type" : "constant",
                    "value" : 12
                  },
                  "allowHTML" : {
                    "type" : "constant",
                    "value" : false
                  },
                  "labelPosition" : {
                    "type" : "constant",
                    "value" : "top"
                  },
                  "labelWidth" : {
                    "type" : "constant",
                    "value" : 4
                  }
                },
                "reference" : "51879880-3385-49f4-aabe-efb3f0a6c99d",
                "hasValidationError" : false,
                "id" : "pbText",
                "description" : ""
              }
            ],
            [
              {
                "type" : "component",
                "dimension" : {
                  "md" : 12,
                  "sm" : 12,
                  "xs" : 12,
                  "lg" : 12
                },
                "propertyValues" : {
                  "labelHidden" : {
                    "type" : "constant",
                    "value" : false
                  },
                  "hidden" : {
                    "type" : "constant",
                    "value" : true
                  },
                  "cssClasses" : {
                    "type" : "constant",
                    "value" : ""
                  },
                  "disabled" : {
                    "type" : "constant",
                    "value" : true
                  },
                  "label" : {
                    "type" : "interpolation",
                    "value" : "Verificado Sistemas"
                  },
                  "dimension" : {
                    "type" : "constant",
                    "value" : 12
                  },
                  "value" : {
                    "type" : "variable",
                    "value" : "solicitud.verificadoSistemas"
                  },
                  "required" : {
                    "type" : "constant",
                    "value" : true
                  },
                  "allowHTML" : {
                    "type" : "constant",
                    "value" : false
                  }
                },
                "reference" : "db91889f-2203-4956-a12c-d66f4e3f0405",
                "hasValidationError" : false,
                "id" : "pbCheckbox",
                "description" : ""
              }
            ],
            [
              {
                "type" : "component",
                "dimension" : {
                  "md" : 12,
                  "sm" : 12,
                  "xs" : 12,
                  "lg" : 12
                },
                "propertyValues" : {
                  "labelHidden" : {
                    "type" : "constant",
                    "value" : false
                  },
                  "hidden" : {
                    "type" : "constant",
                    "value" : false
                  },
                  "labelPosition" : {
                    "type" : "constant",
                    "value" : "top"
                  },
                  "cssClasses" : {
                    "type" : "constant",
                    "value" : ""
                  },
                  "labelWidth" : {
                    "type" : "constant",
                    "value" : 1
                  },
                  "readOnly" : {
                    "type" : "constant",
                    "value" : false
                  },
                  "label" : {
                    "type" : "interpolation",
                    "value" : "Verificado Comentario"
                  },
                  "placeholder" : {
                    "type" : "constant"
                  },
                  "type" : {
                    "type" : "constant",
                    "value" : "text"
                  },
                  "dimension" : {
                    "type" : "constant",
                    "value" : 12
                  },
                  "value" : {
                    "type" : "variable",
                    "value" : "solicitud.verificadoComentario"
                  },
                  "required" : {
                    "type" : "constant",
                    "value" : true
                  },
                  "allowHTML" : {
                    "type" : "constant",
                    "value" : false
                  },
                  "minLength" : {
                    "type" : "constant",
                    "value" : ""
                  },
                  "maxLength" : {
                    "type" : "constant",
                    "value" : ""
                  },
                  "debounce" : {
                    "type" : "constant",
                    "value" : 0
                  },
                  "min" : {
                    "type" : "constant"
                  },
                  "max" : {
                    "type" : "constant"
                  },
                  "step" : {
                    "type" : "constant",
                    "value" : 1
                  }
                },
                "reference" : "8d2520f4-2a7b-4792-823a-a3441c283c16",
                "hasValidationError" : false,
                "id" : "pbInput",
                "description" : ""
              }
            ],
            [
              {
                "type" : "component",
                "dimension" : {
                  "md" : 12,
                  "sm" : 12,
                  "xs" : 12,
                  "lg" : 12
                },
                "propertyValues" : {
                  "cssClasses" : {
                    "type" : "constant",
                    "value" : ""
                  },
                  "hidden" : {
                    "type" : "constant",
                    "value" : false
                  },
                  "disabled" : {
                    "type" : "constant",
                    "value" : false
                  },
                  "required" : {
                    "type" : "constant",
                    "value" : true
                  },
                  "allowHTML" : {
                    "type" : "constant",
                    "value" : false
                  },
                  "labelHidden" : {
                    "type" : "constant",
                    "value" : false
                  },
                  "label" : {
                    "type" : "interpolation",
                    "value" : "Desarrollador Responsable"
                  },
                  "labelPosition" : {
                    "type" : "constant",
                    "value" : "top"
                  },
                  "labelWidth" : {
                    "type" : "constant",
                    "value" : 1
                  },
                  "placeholder" : {
                    "type" : "interpolation"
                  },
                  "availableValues" : {
                    "type" : "expression",
                    "value" : "respDesarrollador"
                  },
                  "displayedKey" : {
                    "type" : "constant",
                    "value" : "userName"
                  },
                  "returnedKey" : {
                    "type" : "constant",
                    "value" : "id"
                  },
                  "value" : {
                    "type" : "variable",
                    "value" : "solicitud.idRespDesarrollador"
                  }
                },
                "reference" : "043a4c29-a7f4-47de-966b-83957fc6ddbd",
                "hasValidationError" : false,
                "id" : "pbSelect"
              }
            ],
            [
              {
                "type" : "component",
                "dimension" : {
                  "xs" : 12,
                  "sm" : 12,
                  "md" : 6,
                  "lg" : 6
                },
                "propertyValues" : {
                  "cssClasses" : {
                    "type" : "constant",
                    "value" : ""
                  },
                  "hidden" : {
                    "type" : "constant",
                    "value" : false
                  },
                  "disabled" : {
                    "type" : "expression",
                    "value" : "$form.$invalid"
                  },
                  "allowHTML" : {
                    "type" : "constant",
                    "value" : false
                  },
                  "label" : {
                    "type" : "interpolation",
                    "value" : "Rechazar"
                  },
                  "alignment" : {
                    "type" : "constant",
                    "value" : "right"
                  },
                  "buttonStyle" : {
                    "type" : "constant",
                    "value" : "danger"
                  },
                  "action" : {
                    "type" : "constant",
                    "value" : "Submit task"
                  },
                  "assign" : {
                    "type" : "constant",
                    "value" : false
                  },
                  "url" : {
                    "type" : "interpolation"
                  },
                  "responseStatusCode" : {
                    "type" : "variable"
                  },
                  "dataToSend" : {
                    "type" : "expression",
                    "value" : "formOutputRechazar"
                  },
                  "dataFromSuccess" : {
                    "type" : "variable"
                  },
                  "closeOnSuccess" : {
                    "type" : "constant",
                    "value" : false
                  },
                  "dataFromError" : {
                    "type" : "variable"
                  },
                  "targetUrlOnSuccess" : {
                    "type" : "interpolation",
                    "value" : "/bonita"
                  },
                  "collectionToModify" : {
                    "type" : "variable"
                  },
                  "modalId" : {
                    "type" : "constant",
                    "value" : ""
                  },
                  "collectionPosition" : {
                    "type" : "constant",
                    "value" : "Last"
                  },
                  "valueToAdd" : {
                    "type" : "constant"
                  },
                  "removeItem" : {
                    "type" : "variable"
                  }
                },
                "reference" : "d7d4e598-365c-4bad-a323-910963951f6e",
                "hasValidationError" : false,
                "id" : "pbButton"
              },
              {
                "type" : "component",
                "dimension" : {
                  "md" : 6,
                  "sm" : 12,
                  "xs" : 12,
                  "lg" : 6
                },
                "propertyValues" : {
                  "removeItem" : {
                    "type" : "variable"
                  },
                  "hidden" : {
                    "type" : "constant",
                    "value" : false
                  },
                  "cssClasses" : {
                    "type" : "constant",
                    "value" : ""
                  },
                  "buttonStyle" : {
                    "type" : "constant",
                    "value" : "success"
                  },
                  "label" : {
                    "type" : "interpolation",
                    "value" : "Aceptar"
                  },
                  "dataToSend" : {
                    "type" : "expression",
                    "value" : "formOutput"
                  },
                  "dataFromError" : {
                    "type" : "variable",
                    "value" : "formOutput._submitError"
                  },
                  "allowHTML" : {
                    "type" : "constant",
                    "value" : false
                  },
                  "labelHidden" : {
                    "type" : "constant",
                    "value" : false
                  },
                  "collectionPosition" : {
                    "type" : "constant"
                  },
                  "targetUrlOnSuccess" : {
                    "type" : "interpolation",
                    "value" : "/bonita"
                  },
                  "action" : {
                    "type" : "constant",
                    "value" : "Submit task"
                  },
                  "collectionToModify" : {
                    "type" : "variable"
                  },
                  "valueToAdd" : {
                    "type" : "expression"
                  },
                  "disabled" : {
                    "type" : "expression",
                    "value" : "$form.$invalid"
                  },
                  "alignment" : {
                    "type" : "constant",
                    "value" : "left"
                  },
                  "dimension" : {
                    "type" : "constant",
                    "value" : 12
                  },
                  "assign" : {
                    "type" : "constant",
                    "value" : false
                  },
                  "url" : {
                    "type" : "interpolation"
                  },
                  "responseStatusCode" : {
                    "type" : "variable"
                  },
                  "dataFromSuccess" : {
                    "type" : "variable"
                  },
                  "closeOnSuccess" : {
                    "type" : "constant",
                    "value" : false
                  },
                  "modalId" : {
                    "type" : "constant",
                    "value" : ""
                  }
                },
                "reference" : "91db075c-1b39-4868-99bc-3763bb0e3a52",
                "hasValidationError" : false,
                "id" : "pbButton",
                "description" : ""
              }
            ],
            [
              {
                "type" : "container",
                "dimension" : {
                  "md" : 12,
                  "sm" : 12,
                  "xs" : 12,
                  "lg" : 12
                },
                "propertyValues" : {
                  "repeatedCollection" : {
                    "type" : "variable"
                  },
                  "hidden" : {
                    "type" : "constant",
                    "value" : false
                  },
                  "cssClasses" : {
                    "type" : "constant",
                    "value" : ""
                  },
                  "dimension" : {
                    "type" : "constant",
                    "value" : 12
                  }
                },
                "reference" : "3141950c-1c31-465d-bbfd-ed0a87e47e67",
                "hasValidationError" : false,
                "id" : "pbContainer",
                "rows" : [
                  [
                    {
                      "type" : "component",
                      "dimension" : {
                        "md" : 12,
                        "sm" : 12,
                        "xs" : 12,
                        "lg" : 12
                      },
                      "propertyValues" : {
                        "allowHtml" : {
                          "type" : "constant",
                          "value" : true
                        },
                        "labelHidden" : {
                          "type" : "constant",
                          "value" : false
                        },
                        "hidden" : {
                          "type" : "expression",
                          "value" : "!solicitud.publicado"
                        },
                        "cssClasses" : {
                          "type" : "constant",
                          "value" : ""
                        },
                        "label" : {
                          "type" : "interpolation",
                          "value" : "Publicado"
                        },
                        "text" : {
                          "type" : "interpolation",
                          "value" : "{{solicitud.publicado}}"
                        },
                        "alignment" : {
                          "type" : "constant",
                          "value" : "left"
                        },
                        "dimension" : {
                          "type" : "constant",
                          "value" : 12
                        },
                        "allowHTML" : {
                          "type" : "constant",
                          "value" : false
                        },
                        "labelPosition" : {
                          "type" : "constant",
                          "value" : "top"
                        },
                        "labelWidth" : {
                          "type" : "constant",
                          "value" : 4
                        }
                      },
                      "reference" : "e018d719-15db-42fe-bb00-626521328f28",
                      "hasValidationError" : false,
                      "id" : "pbText",
                      "description" : ""
                    }
                  ],
                  [
                    {
                      "type" : "component",
                      "dimension" : {
                        "md" : 12,
                        "sm" : 12,
                        "xs" : 12,
                        "lg" : 12
                      },
                      "propertyValues" : {
                        "allowHtml" : {
                          "type" : "constant",
                          "value" : true
                        },
                        "labelHidden" : {
                          "type" : "constant",
                          "value" : false
                        },
                        "hidden" : {
                          "type" : "expression",
                          "value" : "!solicitud.idRespControlCalidad"
                        },
                        "cssClasses" : {
                          "type" : "constant",
                          "value" : ""
                        },
                        "label" : {
                          "type" : "interpolation",
                          "value" : "Id Resp Control Calidad"
                        },
                        "text" : {
                          "type" : "interpolation",
                          "value" : "{{solicitud.idRespControlCalidad}}"
                        },
                        "alignment" : {
                          "type" : "constant",
                          "value" : "left"
                        },
                        "dimension" : {
                          "type" : "constant",
                          "value" : 12
                        }
                      },
                      "reference" : "62329639-c979-4c41-a793-665ba7c72c07",
                      "hasValidationError" : false,
                      "id" : "pbText",
                      "description" : ""
                    }
                  ],
                  [
                    {
                      "type" : "component",
                      "dimension" : {
                        "md" : 12,
                        "sm" : 12,
                        "xs" : 12,
                        "lg" : 12
                      },
                      "propertyValues" : {
                        "labelHidden" : {
                          "type" : "constant",
                          "value" : false
                        },
                        "hidden" : {
                          "type" : "expression",
                          "value" : "!solicitud.aprobadoCC"
                        },
                        "cssClasses" : {
                          "type" : "constant",
                          "value" : ""
                        },
                        "disabled" : {
                          "type" : "constant",
                          "value" : true
                        },
                        "label" : {
                          "type" : "interpolation",
                          "value" : "Aprobado C C"
                        },
                        "dimension" : {
                          "type" : "constant",
                          "value" : 12
                        },
                        "value" : {
                          "type" : "variable",
                          "value" : "solicitud.aprobadoCC"
                        }
                      },
                      "reference" : "c6f111a9-151a-4a17-bf72-4fc93d7e3504",
                      "hasValidationError" : false,
                      "id" : "pbCheckbox",
                      "description" : ""
                    }
                  ],
                  [
                    {
                      "type" : "component",
                      "dimension" : {
                        "md" : 12,
                        "sm" : 12,
                        "xs" : 12,
                        "lg" : 12
                      },
                      "propertyValues" : {
                        "hidden" : {
                          "type" : "constant",
                          "value" : true
                        },
                        "level" : {
                          "type" : "constant",
                          "value" : "Level 4"
                        },
                        "cssClasses" : {
                          "type" : "constant",
                          "value" : ""
                        },
                        "text" : {
                          "type" : "interpolation",
                          "value" : "Comentarios Desarrollo C C"
                        },
                        "alignment" : {
                          "type" : "constant",
                          "value" : "left"
                        },
                        "dimension" : {
                          "type" : "constant",
                          "value" : 12
                        },
                        "allowHTML" : {
                          "type" : "constant",
                          "value" : false
                        }
                      },
                      "reference" : "c702328a-0e73-4a0a-b3a1-67ffa8ad7f13",
                      "hasValidationError" : false,
                      "id" : "pbTitle",
                      "description" : ""
                    }
                  ],
                  [
                    {
                      "type" : "container",
                      "dimension" : {
                        "md" : 12,
                        "sm" : 12,
                        "xs" : 12,
                        "lg" : 12
                      },
                      "propertyValues" : {
                        "repeatedCollection" : {
                          "type" : "variable",
                          "value" : "solicitud.comentariosDesarrolloCC"
                        },
                        "hidden" : {
                          "type" : "constant",
                          "value" : false
                        },
                        "cssClasses" : {
                          "type" : "constant",
                          "value" : ""
                        },
                        "dimension" : {
                          "type" : "constant",
                          "value" : 12
                        }
                      },
                      "reference" : "0f991935-60c2-4435-91e2-519573facb09",
                      "hasValidationError" : false,
                      "id" : "pbContainer",
                      "rows" : [
                        [
                          {
                            "type" : "component",
                            "dimension" : {
                              "md" : 12,
                              "sm" : 12,
                              "xs" : 12,
                              "lg" : 12
                            },
                            "propertyValues" : {
                              "allowHtml" : {
                                "type" : "constant",
                                "value" : true
                              },
                              "labelHidden" : {
                                "type" : "constant",
                                "value" : false
                              },
                              "hidden" : {
                                "type" : "expression",
                                "value" : "!solicitud.comentariosDesarrolloCC"
                              },
                              "cssClasses" : {
                                "type" : "constant",
                                "value" : ""
                              },
                              "label" : {
                                "type" : "interpolation",
                                "value" : "Comentarios Desarrollo C C"
                              },
                              "text" : {
                                "type" : "interpolation",
                                "value" : "{{solicitud.comentariosDesarrolloCC}}"
                              },
                              "alignment" : {
                                "type" : "constant",
                                "value" : "left"
                              },
                              "dimension" : {
                                "type" : "constant",
                                "value" : 12
                              }
                            },
                            "reference" : "fa54c210-c6d5-4600-b3aa-7dbbae72d600",
                            "hasValidationError" : false,
                            "id" : "pbText",
                            "description" : ""
                          }
                        ]
                      ]
                    }
                  ],
                  [
                    {
                      "type" : "component",
                      "dimension" : {
                        "md" : 12,
                        "sm" : 12,
                        "xs" : 12,
                        "lg" : 12
                      },
                      "propertyValues" : {
                        "labelHidden" : {
                          "type" : "constant",
                          "value" : false
                        },
                        "hidden" : {
                          "type" : "expression",
                          "value" : "!solicitud.logsCorrectos"
                        },
                        "cssClasses" : {
                          "type" : "constant",
                          "value" : ""
                        },
                        "disabled" : {
                          "type" : "constant",
                          "value" : true
                        },
                        "label" : {
                          "type" : "interpolation",
                          "value" : "Logs Correctos"
                        },
                        "dimension" : {
                          "type" : "constant",
                          "value" : 12
                        },
                        "value" : {
                          "type" : "variable",
                          "value" : "solicitud.logsCorrectos"
                        },
                        "required" : {
                          "type" : "constant",
                          "value" : false
                        },
                        "allowHTML" : {
                          "type" : "constant",
                          "value" : false
                        }
                      },
                      "reference" : "98ffa0a9-4ec2-43a4-bf82-c197f7f002ea",
                      "hasValidationError" : false,
                      "id" : "pbCheckbox",
                      "description" : ""
                    }
                  ]
                ]
              }
            ],
            [
              {
                "type" : "component",
                "dimension" : {
                  "md" : 12,
                  "sm" : 12,
                  "xs" : 12,
                  "lg" : 12
                },
                "propertyValues" : {
                  "allowHTML" : {
                    "type" : "constant",
                    "value" : true
                  },
                  "allowHtml" : {
                    "type" : "constant",
                    "value" : true
                  },
                  "labelHidden" : {
                    "type" : "constant",
                    "value" : true
                  },
                  "hidden" : {
                    "type" : "expression",
                    "value" : "!formOutput._submitError.message"
                  },
                  "cssClasses" : {
                    "type" : "constant",
                    "value" : "alert alert-danger col-lg-6 col-lg-offset-3"
                  },
                  "label" : {
                    "type" : "interpolation"
                  },
                  "text" : {
                    "type" : "interpolation",
                    "value" : "<strong>Debug message</strong>\n<br/>\n{{formOutput._submitError.message}}\n{{submit_errors_list}}"
                  },
                  "alignment" : {
                    "type" : "constant",
                    "value" : "left"
                  },
                  "dimension" : {
                    "type" : "constant",
                    "value" : 12
                  }
                },
                "reference" : "3279da15-2453-4374-87c5-edebad1187b9",
                "hasValidationError" : false,
                "id" : "pbText",
                "description" : ""
              }
            ]
          ]
        }
      }
    ]
  ],
  "variables" : {
    "task" : {
      "type" : "url",
      "value" : [
        "../API/bpm/userTask/{{taskId}}"
      ],
      "exposed" : false
    },
    "submit_errors_list" : {
      "type" : "expression",
      "value" : [
        "if($data.formOutput && $data.formOutput._submitError && $data.formOutput._submitError.explanations){",
        "\tconst liElements = $data.formOutput._submitError.explanations",
        "\t\t.filter(cause => cause !== null)",
        "\t\t.map(cause => \"<li>\" + cause + \"</li>\")",
        "\t\t.join('');",
        "\tif(liElements){",
        "\t\treturn \"<ul>\" + liElements + \"</ul>\";",
        "\t}",
        "}"
      ],
      "exposed" : false
    },
    "solicitud" : {
      "type" : "url",
      "value" : [
        "../{{context.solicitud_ref.link}}"
      ],
      "exposed" : false
    },
    "formOutput" : {
      "type" : "expression",
      "value" : [
        "if( $data.solicitud ){",
        "\treturn {",
        "\t\t//map solicitud variable to expected task contract input",
        "\t\tsolicitudInput: {",
        "\t\t\tverificadoSistemas: $data.solicitud.verificadoSistemas = true,",
        "\t\t\tverificadoComentario: $data.solicitud.verificadoComentario !== undefined ? $data.solicitud.verificadoComentario : null,",
        "\t\t\tidRespDesarrollador: $data.solicitud.idRespDesarrollador !== undefined ? $data.solicitud.idRespDesarrollador : null",
        "\t\t}",
        "\t}",
        "}"
      ],
      "exposed" : false
    },
    "context" : {
      "type" : "url",
      "value" : [
        "../API/bpm/userTask/{{taskId}}/context"
      ],
      "exposed" : false
    },
    "taskId" : {
      "type" : "urlparameter",
      "value" : [
        "id"
      ],
      "exposed" : false
    },
    "respDesarrollador" : {
      "type" : "url",
      "value" : [
        "../API/identity/user?c=20&f=manager_id=15"
      ],
      "exposed" : false
    },
    "formOutputRechazar" : {
      "type" : "expression",
      "value" : [
        "if( $data.solicitud ){",
        "\treturn {",
        "\t\t//map solicitud variable to expected task contract input",
        "\t\tsolicitudInput: {",
        "\t\t\tverificadoSistemas: $data.solicitud.verificadoSistemas = false,",
        "\t\t\tverificadoComentario: $data.solicitud.verificadoComentario !== undefined ? $data.solicitud.verificadoComentario : null,",
        "\t\t\tidRespDesarrollador: $data.solicitud.idRespDesarrollador !== undefined ? $data.solicitud.idRespDesarrollador : null",
        "\t\t}",
        "\t}",
        "}"
      ],
      "exposed" : false
    }
  },
  "assets" : [
    {
      "id" : "b3642208-8314-4295-837a-695319b488df",
      "name" : "style.css",
      "type" : "css",
      "order" : 0,
      "external" : false
    },
    {
      "id" : "9a08c324-af9f-4348-9d81-9f2e29be29fd",
      "name" : "localization.json",
      "type" : "json",
      "order" : 0,
      "external" : false
    }
  ],
  "inactiveAssets" : [ ],
  "webResources" : [ ],
  "hasValidationError" : false
}